app.py
streamgit/__init__.py
streamgit/cli.py
streamgit/config.py
streamgit/detector.py
streamgit/git_utils.py
streamgit/github_utils.py
streamgit/ui.py
gitstarter-0.1.0.dist-info/LICENSE.md
gitstarter-0.1.0.dist-info/METADATA
gitstarter-0.1.0.dist-info/WHEEL
gitstarter-0.1.0.dist-info/entry_points.txt
gitstarter-0.1.0.dist-info/top_level.txt
gitstarter-0.1.0.dist-info/RECORD
