Metadata-Version: 2.1
Name: gitstarter
Version: 0.1.0
Summary: Hybrid Streamlit UI: automates Git-CLI + GitHub API workflows
Home-page: https://github.com/reprompts/gitstarter
Author: RePromptsQuest
Author-email: repromptsquest@gmail.com
Classifier: Programming Language :: Python :: 3
Classifier: License :: OSI Approved :: MIT License
Classifier: Operating System :: OS Independent
Classifier: Intended Audience :: Developers
Classifier: Environment :: Web Environment
Classifier: Topic :: Software Development :: Version Control
Classifier: Topic :: Utilities
Requires-Python: >=3.7
License-File: LICENSE.md
Requires-Dist: streamlit>=1.0
Requires-Dist: GitPython>=3.1
Requires-Dist: PyGithub>=1.55
